.VERSION
AUTHORS.rst
CONTRIBUTING.rst
HISTORY.rst
LICENSE
MANIFEST.in
Pipfile
Pipfile.lock
README.rst
USAGE.rst
dev-requirements.txt
requirements.txt
setup.cfg
setup.py
docs/Makefile
docs/authors.rst
docs/conf.py
docs/contributing.rst
docs/history.rst
docs/index.rst
docs/installation.rst
docs/readme.rst
docs/usage.rst
myawesometest2lib/.VERSION
myawesometest2lib/AUTHORS.rst
myawesometest2lib/CONTRIBUTING.rst
myawesometest2lib/HISTORY.rst
myawesometest2lib/LICENSE
myawesometest2lib/Pipfile
myawesometest2lib/Pipfile.lock
myawesometest2lib/README.rst
myawesometest2lib/USAGE.rst
myawesometest2lib/__init__.py
myawesometest2lib/_version.py
myawesometest2lib/dev-requirements.txt
myawesometest2lib/myawesometest2lib.py
myawesometest2lib/myawesometest2libexceptions.py
myawesometest2lib/requirements.txt
myawesometest2lib.egg-info/PKG-INFO
myawesometest2lib.egg-info/SOURCES.txt
myawesometest2lib.egg-info/dependency_links.txt
myawesometest2lib.egg-info/not-zip-safe
myawesometest2lib.egg-info/top_level.txt
myawesometest2lib/__pycache__/__init__.cpython-37.pyc
myawesometest2lib/__pycache__/_version.cpython-37.pyc