Metadata-Version: 1.1
Name: myawesometest2lib
Version: 0.1.0
Summary: A template to create python libraries
Home-page: https://github.com/RynoM/MyAwesomeTest2.git
Author: Ryno Marree
Author-email: ryno.marree@hotmail.com
License: MIT
Keywords: myawesometest2lib
Platform: UNKNOWN
Classifier: Development Status :: 6 - Mature
Classifier: Intended Audience :: Developers
Classifier: License :: OSI Approved :: MIT License
Classifier: Natural Language :: English
Classifier: Programming Language :: Python :: 3.7
